cleancc/__init__.py
cleancc/clean.py
cleancc/stopword/stopwords.txt
cleancc-0.1.0.dist-info/LICENSE
cleancc-0.1.0.dist-info/METADATA
cleancc-0.1.0.dist-info/WHEEL
cleancc-0.1.0.dist-info/top_level.txt
cleancc-0.1.0.dist-info/RECORD
