Metadata-Version: 2.1
Name: cleancc
Version: 0.1.0
Summary: Data list cleaning
Home-page: https://github.com/Amiee-well/clean
Author: Lux
Author-email: 1223411083@qq.com
License: UNKNOWN
Platform: UNKNOWN
Classifier: Programming Language :: Python :: 3
Classifier: License :: OSI Approved :: MIT License
Classifier: Operating System :: OS Independent
